pytest_lazyfixture.py
pytest_lazy_fixture-0.6.2.dist-info/LICENSE
pytest_lazy_fixture-0.6.2.dist-info/METADATA
pytest_lazy_fixture-0.6.2.dist-info/WHEEL
pytest_lazy_fixture-0.6.2.dist-info/entry_points.txt
pytest_lazy_fixture-0.6.2.dist-info/top_level.txt
pytest_lazy_fixture-0.6.2.dist-info/RECORD
