Metadata-Version: 2.1
Name: pytest-lazy-fixture
Version: 0.6.2
Summary: It helps to use fixtures in pytest.mark.parametrize
Home-page: https://github.com/tvorog/pytest-lazy-fixture
Author: Marsel Zaripov
Author-email: marszaripov@gmail.com
Maintainer: Marsel Zaripov
Maintainer-email: marszaripov@gmail.com
License: MIT
Platform: UNKNOWN
Classifier: Development Status :: 4 - Beta
Classifier: Framework :: Pytest
Classifier: Intended Audience :: Developers
Classifier: Topic :: Software Development :: Testing
Classifier: Programming Language :: Python
Classifier: Programming Language :: Python :: 2
Classifier: Programming Language :: Python :: 2.7
Classifier: Programming Language :: Python :: 3
Classifier: Programming Language :: Python :: 3.4
Classifier: Programming Language :: Python :: 3.5
Classifier: Programming Language :: Python :: 3.6
Classifier: Programming Language :: Python :: 3.7
Classifier: Programming Language :: Python :: Implementation :: CPython
Classifier: Programming Language :: Python :: Implementation :: PyPy
Classifier: Operating System :: OS Independent
Classifier: License :: OSI Approved :: MIT License
Requires-Dist: pytest (>=3.2.5)
